knotisapi/__init__.py
knotisapi/knotis.py
tests/__init__.py
tests/test_knotis.py
knotisapi-0.0.1.dist-info/METADATA
knotisapi-0.0.1.dist-info/WHEEL
knotisapi-0.0.1.dist-info/top_level.txt
knotisapi-0.0.1.dist-info/RECORD
